medikit/__init__.py
medikit/__main__.py
medikit/_version.py
medikit/compat.py
medikit/events.py
medikit/file.py
medikit/globals.py
medikit/pipeline.py
medikit/settings.py
medikit/structs.py
medikit/testing.py
medikit/utils.py
medikit/commands/__init__.py
medikit/commands/base.py
medikit/commands/init.py
medikit/commands/main.py
medikit/commands/pipeline.py
medikit/commands/update.py
medikit/commands/utils.py
medikit/config/__init__.py
medikit/config/defaults.py
medikit/config/loader.py
medikit/config/registry.py
medikit/feature/__init__.py
medikit/feature/django.py
medikit/feature/docker.py
medikit/feature/format.py
medikit/feature/git.py
medikit/feature/kube.py
medikit/feature/nodejs.py
medikit/feature/pylint.py
medikit/feature/pytest.py
medikit/feature/python.py
medikit/feature/sphinx.py
medikit/feature/webpack.py
medikit/feature/yapf.py
medikit/feature/make/__init__.py
medikit/feature/make/config.py
medikit/feature/make/events.py
medikit/feature/make/resources.py
medikit/feature/make/utils.py
medikit/feature/template/Projectfile.j2
medikit/feature/template/console_script/__main__.py.j2
medikit/feature/template/django/manage.py.j2
medikit/feature/template/django/settings.py.j2
medikit/feature/template/django/urls.py.j2
medikit/feature/template/django/wsgi.py.j2
medikit/feature/template/pytest/coveragerc.j2
medikit/feature/template/pytest/travis.yml.j2
medikit/feature/template/python/package_init.py.j2
medikit/feature/template/python/setup.py.j2
medikit/feature/template/yapf/style.yapf.j2
medikit/resources/__init__.py
medikit/resources/configparser.py
medikit/steps/__init__.py
medikit/steps/base.py
medikit/steps/exec.py
medikit/steps/install.py
medikit/steps/version.py
medikit/steps/utils/__init__.py
medikit/steps/utils/process.py
medikit-0.8.0.dist-info/METADATA
medikit-0.8.0.dist-info/WHEEL
medikit-0.8.0.dist-info/entry_points.txt
medikit-0.8.0.dist-info/top_level.txt
medikit-0.8.0.dist-info/RECORD
