Metadata-Version: 2.1
Name: medikit
Version: 0.8.0
Summary: Opinionated python 3.5+ project management.
Home-page: https://python-medikit.github.io/
Author: Romain Dorgueil
Author-email: romain@dorgueil.net
License: Apache License, Version 2.0
Download-URL: https://github.com/python-medikit/medikit/archive/0.8.0.tar.gz
Platform: UNKNOWN
Requires-Python: >=3.5
Requires-Dist: git-semver (~=0.3.2)
Requires-Dist: jinja2 (~=2.10)
Requires-Dist: mondrian (~=0.8)
Requires-Dist: packaging (~=20.0)
Requires-Dist: pip-tools (~=4.5.0)
Requires-Dist: semantic-version (<2.7)
Requires-Dist: stevedore (~=3.0)
Requires-Dist: whistle (~=1.0)
Requires-Dist: yapf (~=0.20)
Provides-Extra: dev
Requires-Dist: black (==20.8b1) ; extra == 'dev'
Requires-Dist: coverage (~=5.3) ; extra == 'dev'
Requires-Dist: isort ; extra == 'dev'
Requires-Dist: pre-commit (~=2.9.0) ; extra == 'dev'
Requires-Dist: pytest (~=6.0) ; extra == 'dev'
Requires-Dist: pytest-cov (~=2.7) ; extra == 'dev'
Requires-Dist: releases (<1.7,>=1.6) ; extra == 'dev'
Requires-Dist: sphinx (~=1.7) ; extra == 'dev'
Requires-Dist: sphinx-sitemap (~=1.0) ; extra == 'dev'
